CHANGELOG.md
MANIFEST.in
README.md
setup.py
tox.ini
outlawg/__init__.py
outlawg/outlawg.py
outlawg.egg-info/PKG-INFO
outlawg.egg-info/SOURCES.txt
outlawg.egg-info/dependency_links.txt
outlawg.egg-info/top_level.txt