Metadata-Version: 1.1
Name: outlawg
Version: 0.1.0
Summary: Not your grandmother's logging tool
Home-page: UNKNOWN
Author: Richard Pappalardo
Author-email: rpappalax@gmail.com
License: MPL2
Keywords: [logging,test]
Platform: UNKNOWN
Classifier: Topic :: Software Development :: Quality Assurance
Classifier: Topic :: Software Development :: Testing
Classifier: Programming Language :: Python
Classifier: Programming Language :: Python :: 2
Classifier: Programming Language :: Python :: 3.4
